budget/__init__.py
budget/admin.py
budget/base_models.py
budget/forms.py
budget/models.py
budget/urls.py
budget/views.py
budget/categories/__init__.py
budget/categories/admin.py
budget/categories/forms.py
budget/categories/models.py
budget/categories/tests.py
budget/categories/urls.py
budget/categories/views.py
budget/categories/migrations/0001_initial.py
budget/categories/migrations/__init__.py
budget/migrations/0001_initial.py
budget/migrations/0002_auto_20150904_1233.py
budget/migrations/0003_auto_20151218_0740.py
budget/migrations/0004_auto_20151218_0741.py
budget/migrations/0005_remove_budgetestimate_repeat.py
budget/migrations/__init__.py
budget/static/css/basic.css
budget/static/css/budget.css
budget/static/css/ie6.css
budget/static/css/print.css
budget/static/css/ui.datepicker.css
budget/static/img/calendar.gif
budget/static/js/basic.js
budget/static/js/ui.datepicker.js
budget/templates/base.html
budget/templates/budget/base.html
budget/templates/budget/blaa.html
budget/templates/budget/dashboard.html
budget/templates/budget/pagination.html
budget/templates/budget/setup.html
budget/templates/budget/budgets/add.html
budget/templates/budget/budgets/blaa.html
budget/templates/budget/budgets/delete.html
budget/templates/budget/budgets/edit.html
budget/templates/budget/budgets/list.html
budget/templates/budget/budgets/show.html
budget/templates/budget/categories/add.html
budget/templates/budget/categories/delete.html
budget/templates/budget/categories/edit.html
budget/templates/budget/categories/list.html
budget/templates/budget/estimates/add.html
budget/templates/budget/estimates/delete.html
budget/templates/budget/estimates/edit.html
budget/templates/budget/estimates/list.html
budget/templates/budget/summaries/summary_list.html
budget/templates/budget/summaries/summary_month.html
budget/templates/budget/summaries/summary_year.html
budget/templates/budget/summaries/summary_year_months.html
budget/templates/budget/transactions/add.html
django_pj_budget-2.3.4.dist-info/LICENSE
django_pj_budget-2.3.4.dist-info/METADATA
django_pj_budget-2.3.4.dist-info/WHEEL
django_pj_budget-2.3.4.dist-info/top_level.txt
django_pj_budget-2.3.4.dist-info/RECORD
